LICENSE.txt
MANIFEST.in
README.md
requirements.txt
setup.cfg
setup.py
humo_utils/__init__.py
humo_utils.egg-info/PKG-INFO
humo_utils.egg-info/SOURCES.txt
humo_utils.egg-info/dependency_links.txt
humo_utils.egg-info/requires.txt
humo_utils.egg-info/top_level.txt
humo_utils/analytic/__init__.py
humo_utils/conversion/__init__.py
humo_utils/conversion/excel/__init__.py
humo_utils/conversion/pdf/__init__.py
humo_utils/datetime_utils/__init__.py
humo_utils/down_file/__init__.py
humo_utils/generates/__init__.py
humo_utils/generates/address.py
humo_utils/generates/area_data.py
humo_utils/generates/card_no.py
humo_utils/generates/mobile.py
humo_utils/generates/name.py
humo_utils/zip/__init__.py