Metadata-Version: 2.1
Name: humo-utils
Version: 0.7
Summary: 小右的常见工具类
Home-page: https://github.com/Mini-Right/HumoUtils
Author: Mini-Right
Author-email: www@anyu.wang
License: MIT
Download-URL: https://github.com/user/reponame/archive/v_01.tar.gz
Keywords: HUMO,UTILS,FastAPI
Platform: UNKNOWN
Classifier: Development Status :: 3 - Alpha
Classifier: Intended Audience :: Developers
Classifier: Topic :: Software Development :: Build Tools
Classifier: License :: OSI Approved :: MIT License
Classifier: Programming Language :: Python :: 3
Classifier: Programming Language :: Python :: 3.4
Classifier: Programming Language :: Python :: 3.5
Classifier: Programming Language :: Python :: 3.6
Classifier: Programming Language :: Python :: 3.7
Classifier: Programming Language :: Python :: 3.8
License-File: LICENSE.txt
